<?xml version='1.0' encoding='UTF-8'?>
<object id="7HRP3chHe4Ro" classes="use-case-step" acceptedChildren=":Proteus-none" acceptedParents="use-case">
  <properties>
    <stringProperty name=":Proteus-name" category="general"><![CDATA[Listado de inmuebles]]></stringProperty>
    <markdownProperty name="description" category="general"><![CDATA[El sistema muestra el listado de inmuebles.]]></markdownProperty>
    <markdownProperty name="comments" category="comments"><![CDATA[]]></markdownProperty>
  </properties>
  <children/>
</object>
